tide/__init__.py
tide/base.py
tide/classifiers.py
tide/influx.py
tide/math.py
tide/meteo.py
tide/metrics.py
tide/plot.py
tide/plumbing.py
tide/processing.py
tide/regressors.py
tide/utils.py
python_tide-0.1.6.dist-info/licenses/LICENSE.md
python_tide-0.1.6.dist-info/WHEEL
python_tide-0.1.6.dist-info/METADATA
python_tide-0.1.6.dist-info/RECORD
