Metadata-Version: 2.4
Name: python-tide
Version: 0.1.6
Summary: Measured data visualization and pipelines creation
Author-email: Baptiste Durand-Estebe <b.durandestebe@gmail.com>
Maintainer-email: Baptiste Durand-Estebe <b.durandestebe@gmail.com>
Requires-Python: >=3.10
Classifier: Development Status :: 4 - Beta
Classifier: Intended Audience :: Developers
Classifier: License :: OSI Approved :: BSD License
Classifier: Programming Language :: Python :: 3
Classifier: Programming Language :: Python :: 3.10
Classifier: Programming Language :: Python :: 3.11
Classifier: Programming Language :: Python :: 3.12
Classifier: Programming Language :: Python :: 3.13
License-File: LICENSE.md
Requires-Dist: numpy>=1.22.4, <2.0
Requires-Dist: pandas>=2.0.0, <3.0
Requires-Dist: scipy>=1.9.1, <2.0
Requires-Dist: bigtree>=0.21.3
Requires-Dist: scikit-learn>=1.2.2, <2.0
Requires-Dist: statsmodels>=0.14.4
Requires-Dist: matplotlib>=3.5.1
Requires-Dist: plotly>=5.3.1
Requires-Dist: requests>=2.32.3
Requires-Dist: influxdb-client>=1.48.0
Requires-Dist: prophet>=1.1.6
Requires-Dist: pytest>=7.0.0 ; extra == "dev"
Requires-Dist: pre-commit>=3.3.3 ; extra == "dev"
Requires-Dist: bump2version>=1.0.1 ; extra == "dev"
Requires-Dist: sphinx>=7.1.0 ; extra == "dev"
Requires-Dist: sphinx-rtd-theme>=2.0.0 ; extra == "dev"
Requires-Dist: sphinx-autodoc-typehints>=1.25.2 ; extra == "dev"
Requires-Dist: myst-parser>=2.0.0 ; extra == "dev"
Requires-Dist: nbsphinx>=0.9.3 ; extra == "dev"
Requires-Dist: sphinx-copybutton>=0.5.2 ; extra == "dev"
Project-URL: Source, https://github.com/BuildingEnergySimulationTools/tide
Provides-Extra: dev
